graph_extract/__init__.py
graph_extract/graph_extract.py
graph_extract-0.0.2.dist-info/LICENSE
graph_extract-0.0.2.dist-info/METADATA
graph_extract-0.0.2.dist-info/WHEEL
graph_extract-0.0.2.dist-info/top_level.txt
graph_extract-0.0.2.dist-info/RECORD
