Metadata-Version: 2.1
Name: graph-extract
Version: 0.0.2
Summary: Library for extracting values from graphs
Home-page: https://github.com/lewisacidic/graph-extract
Author: Rich Lewis
Author-email: opensource@richlew.is
License: MIT License
Platform: UNKNOWN
Classifier: Development Status :: 3 - Alpha
Classifier: Intended Audience :: Science/Research
Classifier: License :: OSI Approved :: MIT License
Requires-Dist: numpy
Requires-Dist: pillow
